[
    {
        "Author": "TomFord5566",
        "Title": "HR會拒接電話嗎?",
        "Time": "2024-12-26T13:04:47",
        "Timestamp": 1735189487,
        "Responses": [
            {
                "Content": "那就是沒了",
                "Vote": "推",
                "User": "gaym19",
                "Time": "12/26 13:05"
            },
            {
                "Content": "你在期待什麼",
                "Vote": "→",
                "User": "snow3804",
                "Time": "12/26 13:05"
            },
            {
                "Content": "沒通知就是沒希望囉",
                "Vote": "→",
                "User": "wwl0909",
                "Time": "12/26 13:05"
            },
            {
                "Content": "朕覺得你可以放棄了",
                "Vote": "→",
                "User": "zyxx",
                "Time": "12/26 13:06"
            },
            {
                "Content": "HR的屁話永遠不用信，台灣HR真的做的超 丟公司的臉，都承諾回電了沒回電答覆還 會跟你說那是正常的你要自己知道= =腦",
                "Vote": "推",
                "User": "suughine",
                "Time": "12/26 13:10"
            },
            {
                "Content": "朕覺得你可以再拗-下",
                "Vote": "→",
                "User": "shotholisi",
                "Time": "12/26 13:11"
            },
            {
                "Content": "因為HR也不在了",
                "Vote": "推",
                "User": "luck9987",
                "Time": "12/26 13:17"
            },
            {
                "Content": "HR的屁話你當真喔",
                "Vote": "推",
                "User": "victorly",
                "Time": "12/26 14:10"
            },
            {
                "Content": "直接打公司分機不可能不接吧",
                "Vote": "→",
                "User": "jy15141312",
                "Time": "12/26 18:46"
            }
        ],
        "UpVote": 4,
        "DownVote": 0,
        "NoVote": 9,
        "Tag": "問卦"
    },
    {
        "Author": "ODFans",
        "Title": "電子支付的頂點是?",
        "Time": "2024-12-26T13:04:47",
        "Timestamp": 1735189487,
        "Responses": [
            {
                "Content": "excelpay可無中生有 資金源源不絕",
                "Vote": "推",
                "User": "james114",
                "Time": "12/26 13:05"
            },
            {
                "Content": "人礦就是電子支付到頂點",
                "Vote": "推",
                "User": "aggressorX",
                "Time": "12/26 13:05"
            },
            {
                "Content": "linepay是第三方支付 働!!!爛股",
                "Vote": "→",
                "User": "jupiterlin",
                "Time": "12/26 13:08"
            },
            {
                "Content": "LinePay在台灣不是已經有電子支付的執照了嗎",
                "Vote": "→",
                "User": "Ilat",
                "Time": "12/26 13:11"
            },
            {
                "Content": "應該穩賠慘，最後全回到現金和刷卡",
                "Vote": "推",
                "User": "edward0811",
                "Time": "12/26 13:12"
            },
            {
                "Content": "我很討厭還要掃二維碼輸入金額的店家， 為什麼其他都能含載具就你要分開",
                "Vote": "噓",
                "User": "B9907143",
                "Time": "12/26 13:15"
            },
            {
                "Content": "Excel支付台灣黑科技獨步全球你敢嘴！",
                "Vote": "→",
                "User": "ez111111",
                "Time": "12/26 13:16"
            },
            {
                "Content": "excelpay",
                "Vote": "→",
                "User": "Tsyu",
                "Time": "12/26 13:17"
            },
            {
                "Content": "有經濟規模才有機會 悠遊卡取得先機卻沒有把握住",
                "Vote": "→",
                "User": "reil",
                "Time": "12/26 14:51"
            },
            {
                "Content": "\\目前的電子支付的頂點是excelpay",
                "Vote": "→",
                "User": "kdn",
                "Time": "12/26 15:19"
            }
        ],
        "UpVote": 4,
        "DownVote": 1,
        "NoVote": 11,
        "Tag": "問卦"
    },
    {
        "Author": "flyslider",
        "Title": "殺殺殺殺殺殺殺 殺無赦 下聯怎對？",
        "Time": "2024-12-26T13:05:05",
        "Timestamp": 1735189505,
        "Responses": [
            {
                "Content": "關關關關關關關 關到死",
                "Vote": "推",
                "User": "CGDGAD",
                "Time": "12/26 13:06"
            },
            {
                "Content": "賴賴賴賴賴賴賴 賴皮鬼",
                "Vote": "推",
                "User": "deerdriver",
                "Time": "12/26 13:06"
            },
            {
                "Content": "科科科科 柯文哲",
                "Vote": "→",
                "User": "snow3804",
                "Time": "12/26 13:06"
            },
            {
                "Content": "清清清清清清清 清有德",
                "Vote": "推",
                "User": "diefox",
                "Time": "12/26 13:07"
            },
            {
                "Content": "哭哭哭哭哭哭哭 夜裡哭",
                "Vote": "推",
                "User": "wubai1119",
                "Time": "12/26 13:07"
            },
            {
                "Content": "頂頂頂頂頂頂頂   頂到肺",
                "Vote": "推",
                "User": "casablanka",
                "Time": "12/26 13:07"
            },
            {
                "Content": "eeeeeeeeeeeeeee excel wwwwwwwwwwwww word",
                "Vote": "→",
                "User": "snow3804",
                "Time": "12/26 13:07"
            },
            {
                "Content": "啊啊啊啊啊啊啊  啊去了",
                "Vote": "→",
                "User": "cauliflower",
                "Time": "12/26 13:07"
            },
            {
                "Content": "党党党党党党党 擋無期",
                "Vote": "推",
                "User": "jupiterlin",
                "Time": "12/26 13:08"
            },
            {
                "Content": "恥恥恥恥恥恥恥，恥無限",
                "Vote": "推",
                "User": "maaaaa",
                "Time": "12/26 13:10"
            },
            {
                "Content": "伐伐伐伐伐伐伐 伐木工",
                "Vote": "推",
                "User": "Cherng9527",
                "Time": "12/26 13:11"
            },
            {
                "Content": "宅宅宅宅宅宅宅 宅到爆",
                "Vote": "推",
                "User": "DPP48",
                "Time": "12/26 13:12"
            },
            {
                "Content": "哈哈哈哈哈哈哈 利波特",
                "Vote": "推",
                "User": "gn00026563",
                "Time": "12/26 13:15"
            },
            {
                "Content": "點點點點點點點 點主官",
                "Vote": "推",
                "User": "givemelife",
                "Time": "12/26 13:16"
            },
            {
                "Content": "關*7 關死你",
                "Vote": "推",
                "User": "asgardgogo",
                "Time": "12/26 13:17"
            },
            {
                "Content": "愛愛愛愛愛愛 戰鬥",
                "Vote": "→",
                "User": "s511320",
                "Time": "12/26 13:17"
            },
            {
                "Content": "塔塔塔塔塔塔塔.  塔綠班",
                "Vote": "→",
                "User": "bingreen",
                "Time": "12/26 13:19"
            },
            {
                "Content": "哭哭哭哭哭哭 哭文哲",
                "Vote": "推",
                "User": "momochacha",
                "Time": "12/26 13:24"
            },
            {
                "Content": "電電電電電電電 電真賺",
                "Vote": "推",
                "User": "konanno1",
                "Time": "12/26 13:25"
            },
            {
                "Content": "愛愛愛愛愛愛愛 愛不完",
                "Vote": "推",
                "User": "whyyeswhynot",
                "Time": "12/26 13:26"
            },
            {
                "Content": "鳥鳥鳥鳥鳥鳥鳥 鳥蟾蜍 犬犬犬犬犬犬犬 犬法官",
                "Vote": "→",
                "User": "konanno1",
                "Time": "12/26 13:26"
            },
            {
                "Content": "對對對對對對對 你收賄",
                "Vote": "推",
                "User": "popobully",
                "Time": "12/26 13:33"
            },
            {
                "Content": "崩崩崩崩崩崩崩 草崩潰",
                "Vote": "推",
                "User": "syk1104",
                "Time": "12/26 13:34"
            },
            {
                "Content": "賴缺德美國金孫沒屁眼",
                "Vote": "→",
                "User": "leechiungyi",
                "Time": "12/26 13:35"
            },
            {
                "Content": "戰戰戰戰戰戰戰 戰你娘",
                "Vote": "推",
                "User": "yzvr",
                "Time": "12/26 13:40"
            },
            {
                "Content": "大大大大大大大 大優惠",
                "Vote": "推",
                "User": "hiphopmei",
                "Time": "12/26 13:45"
            },
            {
                "Content": "姦姦姦姦姦姦姦 姦人妻",
                "Vote": "推",
                "User": "SALEENS7LM",
                "Time": "12/26 13:54"
            },
            {
                "Content": "查查查查查查查 查不出",
                "Vote": "推",
                "User": "jason880331",
                "Time": "12/26 14:01"
            },
            {
                "Content": "說說說說說說說 你愛我",
                "Vote": "推",
                "User": "bravo223999",
                "Time": "12/26 14:03"
            },
            {
                "Content": "騙騙騙騙騙騙騙 騙大位",
                "Vote": "推",
                "User": "victorly",
                "Time": "12/26 14:08"
            },
            {
                "Content": "幹幹幹幹幹幹幹 幹你媽",
                "Vote": "推",
                "User": "wsad50232",
                "Time": "12/26 14:59"
            }
        ],
        "UpVote": 27,
        "DownVote": 1,
        "NoVote": 11,
        "Tag": "問卦"
    },
    {
        "Author": "ParkChanWook",
        "Title": ".doc",
        "Time": "2024-12-26T13:06:50",
        "Timestamp": 1735189610,
        "Responses": [
            {
                "Content": "六十幾歲的人用.doc差不多ㄅ",
                "Vote": "推",
                "User": "JinCheng5566",
                "Time": "12/26 13:07"
            },
            {
                "Content": "有些是古老的程式只能產出doc",
                "Vote": "→",
                "User": "LFD",
                "Time": "12/26 13:07"
            },
            {
                "Content": "有舊盜版啊",
                "Vote": "推",
                "User": "zephyr105",
                "Time": "12/26 13:07"
            },
            {
                "Content": "因為還在用2003啊",
                "Vote": "推",
                "User": "duelaylomo",
                "Time": "12/26 13:07"
            },
            {
                "Content": "硬要改docx輸出可能會有很神奇的bug",
                "Vote": "→",
                "User": "LFD",
                "Time": "12/26 13:08"
            },
            {
                "Content": "多的是還在2003的= =",
                "Vote": "→",
                "User": "harryron9",
                "Time": "12/26 13:08"
            },
            {
                "Content": "新的一套幾千元 不想買吧",
                "Vote": "→",
                "User": "zephyr105",
                "Time": "12/26 13:08"
            },
            {
                "Content": "97還可以再戰十年 沒問題的",
                "Vote": "→",
                "User": "Ilat",
                "Time": "12/26 13:09"
            },
            {
                "Content": "都賺幾千萬幾億比特幣了，幾千塊都不花太",
                "Vote": "→",
                "User": "kxloft",
                "Time": "12/26 13:09"
            },
            {
                "Content": "我用2007",
                "Vote": "→",
                "User": "theeht",
                "Time": "12/26 13:09"
            },
            {
                "Content": "盜版不會更新阿0.0",
                "Vote": "→",
                "User": "su4vu6",
                "Time": "12/26 13:10"
            }
        ],
        "UpVote": 3,
        "DownVote": 0,
        "NoVote": 9,
        "Tag": "問卦"
    },
    {
        "Author": "Junt418",
        "Title": "1500萬現金有多重",
        "Time": "2024-12-26T13:06:56",
        "Timestamp": 1735189616,
        "Responses": [
            {
                "Content": "用excel搬就好了 才幾kb",
                "Vote": "→",
                "User": "rz759",
                "Time": "12/26 13:07"
            },
            {
                "Content": "電子檔這麼重",
                "Vote": "推",
                "User": "kevin0515",
                "Time": "12/26 13:07"
            },
            {
                "Content": "20幾公斤",
                "Vote": "→",
                "User": "preisner",
                "Time": "12/26 13:07"
            },
            {
                "Content": "你是第87個問的啦 25公斤啦幹！",
                "Vote": "→",
                "User": "Ilat",
                "Time": "12/26 13:08"
            },
            {
                "Content": "小草還是趕快進口橘子吧",
                "Vote": "推",
                "User": "apparel",
                "Time": "12/26 13:08"
            },
            {
                "Content": "存excel放在USB就可以輕鬆帶出國了",
                "Vote": "推",
                "User": "QBoyo",
                "Time": "12/26 13:08"
            },
            {
                "Content": "可以問一下陳明文 300萬的5倍",
                "Vote": "推",
                "User": "jonejone",
                "Time": "12/26 13:08"
            },
            {
                "Content": "1500萬1元硬幣  扛10里山路",
                "Vote": "推",
                "User": "fp737",
                "Time": "12/26 13:08"
            },
            {
                "Content": "二十幾公斤",
                "Vote": "推",
                "User": "HellFly",
                "Time": "12/26 13:08"
            },
            {
                "Content": "200公斤 跟我台南絡腮鬍保全朋友一樣重",
                "Vote": "→",
                "User": "luciffar",
                "Time": "12/26 13:09"
            },
            {
                "Content": "館長準備拍 扛紙鈔的段影音了",
                "Vote": "→",
                "User": "alco7",
                "Time": "12/26 13:09"
            },
            {
                "Content": "可以搭五次高鐵",
                "Vote": "推",
                "User": "rex0217",
                "Time": "12/26 13:09"
            },
            {
                "Content": "拍電影時誰適合演拉著23kg現金的yahoo?",
                "Vote": "→",
                "User": "cdmlin",
                "Time": "12/26 13:10"
            },
            {
                "Content": "看來可以買23-25KG的橘子",
                "Vote": "推",
                "User": "apparel",
                "Time": "12/26 13:10"
            },
            {
                "Content": "把兩國海關當成塑膠",
                "Vote": "→",
                "User": "milk250",
                "Time": "12/26 13:10"
            },
            {
                "Content": "行李箱拉到市長室關海關什麼事?",
                "Vote": "→",
                "User": "cdmlin",
                "Time": "12/26 13:14"
            },
            {
                "Content": "拉你妹 起訴書有寫市長室膩？",
                "Vote": "推",
                "User": "d12345631",
                "Time": "12/26 13:15"
            },
            {
                "Content": "以後憨鳥上班薪水都用隨身碟發到excel裡。",
                "Vote": "→",
                "User": "dsfrf",
                "Time": "12/26 13:22"
            },
            {
                "Content": "一個行動硬碟那麼重吧",
                "Vote": "推",
                "User": "max011060",
                "Time": "12/26 13:27"
            },
            {
                "Content": "領1600然後柯收1500，再於不知何時交給許 ！？所以1500萬的現金憑空消失？帶出國海 關嚇了嗎？這樣還掰的下去",
                "Vote": "噓",
                "User": "JY1102",
                "Time": "12/26 13:31"
            },
            {
                "Content": "存在Excel沒重量",
                "Vote": "推",
                "User": "pastevil",
                "Time": "12/26 13:42"
            },
            {
                "Content": "25公斤呀",
                "Vote": "→",
                "User": "xx5244",
                "Time": "12/26 13:51"
            },
            {
                "Content": "鄉民是不是忘了有2000元鈔票",
                "Vote": "噓",
                "User": "eastwindow",
                "Time": "12/26 14:42"
            },
            {
                "Content": "對啦，全世界就你最聰明想到有2000元鈔 票，大家都想不到",
                "Vote": "噓",
                "User": "b4824583",
                "Time": "12/26 14:53"
            },
            {
                "Content": "大概就是一個空槓槓鈴的重量而已",
                "Vote": "推",
                "User": "tigotigo5566",
                "Time": "12/26 15:00"
            },
            {
                "Content": "講兩千元鈔票的知道兩千市面流通率嗎? 要湊到一千五百萬你要跑幾間銀行? 真這樣提領就超明顯怎麼可能追不到 還用某時某地幹嘛 笑死",
                "Vote": "推",
                "User": "nico78628",
                "Time": "12/26 15:56"
            },
            {
                "Content": "我都用excel檔存在usb帶著走",
                "Vote": "推",
                "User": "leonsand009",
                "Time": "12/27 15:31"
            }
        ],
        "UpVote": 15,
        "DownVote": 3,
        "NoVote": 19,
        "Tag": "問卦"
    },
    {
        "Author": "andrewmiho",
        "Title": "分到起訴38年延押庭的法官怎想？",
        "Time": "2024-12-26T13:07:30",
        "Timestamp": 1735189650,
        "Responses": [
            {
                "Content": "升官發財了",
                "Vote": "→",
                "User": "puritylife",
                "Time": "12/26 13:08"
            },
            {
                "Content": "噫 中了！",
                "Vote": "推",
                "User": "cgluck",
                "Time": "12/26 13:09"
            },
            {
                "Content": "升官發財咯 爽啊",
                "Vote": "噓",
                "User": "cs09312",
                "Time": "12/26 13:09"
            },
            {
                "Content": "升官發財就等今天了",
                "Vote": "→",
                "User": "preisner",
                "Time": "12/26 13:09"
            },
            {
                "Content": "我先請假1個月",
                "Vote": "→",
                "User": "kumori",
                "Time": "12/26 13:09"
            },
            {
                "Content": "想當大法官嗎",
                "Vote": "推",
                "User": "DPP48",
                "Time": "12/26 13:10"
            },
            {
                "Content": "台版基督山恩仇錄",
                "Vote": "→",
                "User": "dg01",
                "Time": "12/26 13:11"
            },
            {
                "Content": "想當大法官嗎XD",
                "Vote": "推",
                "User": "SuperTaco",
                "Time": "12/26 13:13"
            },
            {
                "Content": "升官官發財",
                "Vote": "→",
                "User": "Malion",
                "Time": "12/26 13:13"
            },
            {
                "Content": "啊，難怪民進党故意打假球",
                "Vote": "→",
                "User": "kattte",
                "Time": "12/26 13:18"
            },
            {
                "Content": "反正可以換法官",
                "Vote": "→",
                "User": "mcucte",
                "Time": "12/26 13:37"
            },
            {
                "Content": "應該是資深法官來審 剩五年退休 審個十 年沒結果 自己一路高升到退休 再拖個10 年 就算政黨輪替到時候要清算幫兇 自己 也老到不用關 或早就享福到死都沒被影響 然後被歷史遺忘 但是後代子孫都可以得 到當初的庇佑 穩賺不賠 年輕法官就要擔 心翻盤時自己還活著",
                "Vote": "推",
                "User": "jimhall",
                "Time": "12/26 14:32"
            },
            {
                "Content": "大好大壞，人生十字路口",
                "Vote": "推",
                "User": "reil",
                "Time": "12/26 14:49"
            }
        ],
        "UpVote": 5,
        "DownVote": 1,
        "NoVote": 14,
        "Tag": "問卦"
    },
    {
        "Author": "xzcb2008",
        "Title": "〓.〓 為什麼喵喵睡搞搞可以這麼可愛？",
        "Time": "2024-12-26T13:07:30",
        "Timestamp": 1735189650,
        "Responses": [
            {
                "Content": "貓貓可愛- -",
                "Vote": "→",
                "User": "JinCheng5566",
                "Time": "12/26 13:08"
            },
            {
                "Content": "可愛 =.=",
                "Vote": "推",
                "User": "dnzteeqrq",
                "Time": "12/26 13:09"
            },
            {
                "Content": "口愛=,,..,,=",
                "Vote": "推",
                "User": "Insania",
                "Time": "12/26 13:10"
            },
            {
                "Content": "貓掌看起來很好吃",
                "Vote": "推",
                "User": "cchh179",
                "Time": "12/26 13:10"
            },
            {
                "Content": "流口水 吸",
                "Vote": "推",
                "User": "hsuanYue",
                "Time": "12/26 13:10"
            },
            {
                "Content": "〓.〓我跟貓貓一樣可愛",
                "Vote": "推",
                "User": "k385476916",
                "Time": "12/26 13:12"
            },
            {
                "Content": "1/7/10符號很醜 貓貓生氣 k仔也很可愛 早上這畫面太好了=.=有夠溫馨",
                "Vote": "→",
                "User": "xzcb2008",
                "Time": "12/26 13:13"
            },
            {
                "Content": "沒有很可愛 大概PR60而已== 一堆曬貓的 你這真的不夠看 很醜 邏輯貓好看很多 這種一般品種貓太弱了",
                "Vote": "推",
                "User": "Dinenger",
                "Time": "12/26 13:15"
            },
            {
                "Content": "貓貓可愛！！！！ 一起睡也會變可愛！",
                "Vote": "推",
                "User": "mk203125",
                "Time": "12/26 13:17"
            },
            {
                "Content": "可愛=.=",
                "Vote": "推",
                "User": "yamato5566",
                "Time": "12/26 13:18"
            },
            {
                "Content": "若有的貓貓都也可以愛的 =.= 阿肥當然也很喜歡黑臉貓",
                "Vote": "→",
                "User": "xzcb2008",
                "Time": "12/26 13:36"
            },
            {
                "Content": "好可愛 好想摸",
                "Vote": "→",
                "User": "DEVIN929",
                "Time": "12/26 13:39"
            },
            {
                "Content": "+9貓可愛",
                "Vote": "推",
                "User": "thisu",
                "Time": "12/26 20:44"
            }
        ],
        "UpVote": 14,
        "DownVote": 0,
        "NoVote": 12,
        "Tag": "問卦"
    },
    {
        "Author": "ffreakk",
        "Title": "資料夾檔名要怎麼取才霸氣",
        "Time": "2024-12-26T13:09:40",
        "Timestamp": 1735189780,
        "Responses": [
            {
                "Content": "30inch",
                "Vote": "推",
                "User": "dai26",
                "Time": "12/26 13:10"
            },
            {
                "Content": "騎士 步兵",
                "Vote": "推",
                "User": "xsc",
                "Time": "12/26 13:11"
            },
            {
                "Content": "軍訓作業 懂的都懂",
                "Vote": "推",
                "User": "maximu",
                "Time": "12/26 13:12"
            }
        ],
        "UpVote": 7,
        "DownVote": 0,
        "NoVote": 2,
        "Tag": "問卦"
    },
    {
        "Author": "az1342001z",
        "Title": "旁邊的人說罪證確鑿",
        "Time": "2024-12-26T13:09:46",
        "Timestamp": 1735189786,
        "Responses": [
            {
                "Content": "肯定是不知道什麼是excel的低學歷",
                "Vote": "推",
                "User": "butten986",
                "Time": "12/26 13:10"
            },
            {
                "Content": "不意外啊 我公司的深綠也都這樣子",
                "Vote": "→",
                "User": "emiya0113",
                "Time": "12/26 13:11"
            },
            {
                "Content": "一堆，你問他有什麼證據，多半說不出來 沒辦法，黨掌握媒體",
                "Vote": "推",
                "User": "Malion",
                "Time": "12/26 13:12"
            },
            {
                "Content": "是不是綠蟾蜍憨鳥樣？",
                "Vote": "→",
                "User": "SDuncan",
                "Time": "12/26 13:13"
            },
            {
                "Content": "如何證明你沒拿錢 首先 你要先準備1500萬 再來 你要證明你沒拿那1500萬 如果沒辦法準備1500萬 那錢就是被你汙了 等你準備好1500萬 我們再來討論你有沒有",
                "Vote": "推",
                "User": "Falagar",
                "Time": "12/26 13:16"
            },
            {
                "Content": "以後憨鳥上班薪水都用隨身碟發到excel裡。",
                "Vote": "→",
                "User": "dsfrf",
                "Time": "12/26 13:22"
            },
            {
                "Content": "因為他的excel裡面也有錢。",
                "Vote": "推",
                "User": "simon9331",
                "Time": "12/26 15:17"
            }
        ],
        "UpVote": 5,
        "DownVote": 0,
        "NoVote": 9,
        "Tag": "問卦"
    },
    {
        "Author": "poopoo50000",
        "Title": "橘子是tangerine，柳橙是orange ",
        "Time": "2024-12-26T13:09:51",
        "Timestamp": 1735189791,
        "Responses": [
            {
                "Content": "好的 歐潤舉",
                "Vote": "→",
                "User": "cs09312",
                "Time": "12/26 13:10"
            },
            {
                "Content": "智商157說是orange你有意見嗎",
                "Vote": "推",
                "User": "zyxx",
                "Time": "12/26 13:10"
            },
            {
                "Content": "naranja",
                "Vote": "→",
                "User": "Israfil",
                "Time": "12/26 13:10"
            },
            {
                "Content": "那個是柯自己寫的",
                "Vote": "→",
                "User": "Atem",
                "Time": "12/26 13:10"
            },
            {
                "Content": "157說orange就是orange 質疑157?",
                "Vote": "→",
                "User": "keane9112",
                "Time": "12/26 13:11"
            },
            {
                "Content": "對外國人來說都沒差啦,他們不會分辨",
                "Vote": "噓",
                "User": "Nikon1992",
                "Time": "12/26 13:11"
            },
            {
                "Content": "柯寫的 那能證明什麼",
                "Vote": "推",
                "User": "threeforw",
                "Time": "12/26 13:11"
            },
            {
                "Content": "明明就是Orenji",
                "Vote": "推",
                "User": "snocia",
                "Time": "12/26 13:11"
            },
            {
                "Content": "小玉出國 我寫小花出國 就能連結滅證?",
                "Vote": "→",
                "User": "threeforw",
                "Time": "12/26 13:12"
            },
            {
                "Content": "tangent",
                "Vote": "推",
                "User": "bye2007",
                "Time": "12/26 13:12"
            },
            {
                "Content": "I don’t car",
                "Vote": "推",
                "User": "moai513",
                "Time": "12/26 13:13"
            },
            {
                "Content": "I do car",
                "Vote": "推",
                "User": "e46m3s15",
                "Time": "12/26 13:16"
            },
            {
                "Content": "那個，我知道你想秀英文，但我在美 國的超市從來沒看過橘子用這個字。 都是用Mandarin",
                "Vote": "推",
                "User": "YHHinNTU",
                "Time": "12/26 13:16"
            },
            {
                "Content": "你敢質疑柯皇英文不及格？？？",
                "Vote": "推",
                "User": "garyway",
                "Time": "12/26 13:17"
            },
            {
                "Content": "orange可以泛指所有柑橘類，一顆橘 子你可以講mandarin或orange，但一 顆橙子只能講orange",
                "Vote": "→",
                "User": "lucifiel1618",
                "Time": "12/26 13:18"
            },
            {
                "Content": "橘是Mandarin..橙才是Orange",
                "Vote": "→",
                "User": "cityport",
                "Time": "12/26 13:19"
            },
            {
                "Content": "說到底柑橘類是東亞原生種，洋鬼子 懂個屁柑橘",
                "Vote": "→",
                "User": "lucifiel1618",
                "Time": "12/26 13:19"
            },
            {
                "Content": "居然有人柑橙橘不分..常識耶",
                "Vote": "→",
                "User": "cityport",
                "Time": "12/26 13:20"
            },
            {
                "Content": "太crazy了",
                "Vote": "推",
                "User": "mkcg5825",
                "Time": "12/26 13:20"
            },
            {
                "Content": "柑橘屬種是Citrus..根本不是Orange 有人國中沒畢業嗎? 生物零分耶",
                "Vote": "→",
                "User": "cityport",
                "Time": "12/26 13:21"
            },
            {
                "Content": "阿北不可能弄錯，所以不是阿北指示",
                "Vote": "→",
                "User": "pieceofcake",
                "Time": "12/26 13:23"
            },
            {
                "Content": "Summer是夏天",
                "Vote": "推",
                "User": "kai0829",
                "Time": "12/26 13:24"
            },
            {
                "Content": "搞不好她真的中文叫橘子英文叫orange，而 且這不是柯寫的嗎",
                "Vote": "→",
                "User": "DPP48",
                "Time": "12/26 13:25"
            },
            {
                "Content": "Kankitsu",
                "Vote": "→",
                "User": "PRME",
                "Time": "12/26 13:26"
            },
            {
                "Content": "你才是菜英文",
                "Vote": "推",
                "User": "gg8n8nd34ss",
                "Time": "12/26 13:31"
            },
            {
                "Content": "待會去晶華吃下午茶，應該不會被羈押吧",
                "Vote": "→",
                "User": "chyou2003",
                "Time": "12/26 13:42"
            },
            {
                "Content": "怎麼可能不知道, 你當檢察官是白癡嗎？",
                "Vote": "→",
                "User": "lain2002",
                "Time": "12/26 13:51"
            },
            {
                "Content": "恁北都說naranja",
                "Vote": "噓",
                "User": "fraser0136",
                "Time": "12/26 14:10"
            },
            {
                "Content": "你可以在Excel寫晶華 1500試看看",
                "Vote": "推",
                "User": "DPP48",
                "Time": "12/26 14:21"
            },
            {
                "Content": "真的是sun of beach",
                "Vote": "推",
                "User": "aggressorX",
                "Time": "12/26 14:34"
            },
            {
                "Content": "真的是智障",
                "Vote": "→",
                "User": "small91051",
                "Time": "12/26 15:14"
            },
            {
                "Content": "對啊，有人不知道？",
                "Vote": "→",
                "User": "your0207",
                "Time": "12/26 15:43"
            },
            {
                "Content": "笑死..把orange超譯成橘子又連結到許芷瑜 的是檢察官好嗎...",
                "Vote": "推",
                "User": "radom",
                "Time": "12/26 16:52"
            },
            {
                "Content": "who car",
                "Vote": "推",
                "User": "n61208",
                "Time": "12/26 17:48"
            }
        ],
        "UpVote": 16,
        "DownVote": 3,
        "NoVote": 27,
        "Tag": "問卦"
    }
]