[
    {
        "Author": "neil136",
        "Title": "財務姐姐傳訊息給我，是什麼意思？",
        "Time": "2025-01-17T19:18:47",
        "Timestamp": 1737112727,
        "Responses": [
            {
                "Content": "他想幹死你",
                "Vote": "噓",
                "User": "cs09312",
                "Time": "01/17 19:19"
            },
            {
                "Content": "彌平缺口的關鍵在你",
                "Vote": "→",
                "User": "brother001",
                "Time": "01/17 19:19"
            },
            {
                "Content": "你聽過安麗嗎?",
                "Vote": "推",
                "User": "Ayreon",
                "Time": "01/17 19:19"
            },
            {
                "Content": "他傳錯人了",
                "Vote": "噓",
                "User": "derrick1220",
                "Time": "01/17 19:21"
            },
            {
                "Content": "報帳有問題來改一下",
                "Vote": "推",
                "User": "stcr3011",
                "Time": "01/17 19:21"
            },
            {
                "Content": "你的財富流動填補她的缺口",
                "Vote": "推",
                "User": "moon0308",
                "Time": "01/17 19:22"
            },
            {
                "Content": "你要違約交割了啦",
                "Vote": "→",
                "User": "sheep125",
                "Time": "01/17 19:34"
            },
            {
                "Content": "我知道你還有錢？",
                "Vote": "推",
                "User": "dbjdx",
                "Time": "01/17 19:35"
            }
        ],
        "UpVote": 6,
        "DownVote": 2,
        "NoVote": 3,
        "Tag": "問卦"
    },
    {
        "Author": "giorno78",
        "Title": "死刑犯如有精神障礙 不得執行死刑 要怎做",
        "Time": "2025-01-17T19:18:54",
        "Timestamp": 1737112734,
        "Responses": [
            {
                "Content": "有病就要看醫生但預算被藍白亂砍光了QQ",
                "Vote": "→",
                "User": "james732",
                "Time": "01/17 19:19"
            },
            {
                "Content": "用鞭刑打到他變正常",
                "Vote": "推",
                "User": "tf010714",
                "Time": "01/17 19:21"
            },
            {
                "Content": "那還有兩兆多的錢哪去了？",
                "Vote": "推",
                "User": "xbearboy",
                "Time": "01/17 19:26"
            },
            {
                "Content": "派精神異常的殺",
                "Vote": "推",
                "User": "edward0811",
                "Time": "01/17 19:31"
            },
            {
                "Content": "改去精神病院關到死。我們國家該蓋一 間 專供精神障礙 罪犯永久封禁治療 性犯罪者無法自控 也判刑關進這裡面強 制治療永久監禁",
                "Vote": "→",
                "User": "kinmengon",
                "Time": "01/17 19:33"
            }
        ],
        "UpVote": 3,
        "DownVote": 0,
        "NoVote": 5,
        "Tag": "問卦"
    },
    {
        "Author": "suzhou",
        "Title": "為何當年認為攤販在國民所得提升就會消失",
        "Time": "2025-01-17T19:19:01",
        "Timestamp": 1737112741,
        "Responses": [
            {
                "Content": "講得好像歐美沒有攤販跟路邊餐車一樣",
                "Vote": "推",
                "User": "kurtsgm",
                "Time": "01/17 19:20"
            },
            {
                "Content": "一定是多少你沒講啊 說不定還沒到",
                "Vote": "→",
                "User": "Ayreon",
                "Time": "01/17 19:20"
            },
            {
                "Content": "不用繳稅低調賺",
                "Vote": "推",
                "User": "sunday0913",
                "Time": "01/17 19:21"
            },
            {
                "Content": "是真的消失很多啊 只是沒有完全到零",
                "Vote": "→",
                "User": "fatdoghusky",
                "Time": "01/17 19:21"
            },
            {
                "Content": "結果政府辦活動都在圖利攤販 但他們也不繳",
                "Vote": "推",
                "User": "heyd",
                "Time": "01/17 19:23"
            },
            {
                "Content": "實質富裕之後但心態窮酸仔很多",
                "Vote": "推",
                "User": "king123",
                "Time": "01/17 19:24"
            },
            {
                "Content": "小蔣沒說錯，因為攤販賺到錢就買店面了",
                "Vote": "推",
                "User": "jackgn",
                "Time": "01/17 19:26"
            },
            {
                "Content": "原來是小蔣遺毒",
                "Vote": "→",
                "User": "raku",
                "Time": "01/17 20:31"
            }
        ],
        "UpVote": 5,
        "DownVote": 0,
        "NoVote": 4,
        "Tag": "問卦"
    },
    {
        "Author": "JEWH",
        "Title": "天氣冷尿尿完會洗手嗎？",
        "Time": "2025-01-17T19:22:25",
        "Timestamp": 1737112945,
        "Responses": [
            {
                "Content": "你家廁所是沒溫水喔",
                "Vote": "→",
                "User": "cs09312",
                "Time": "01/17 19:22"
            },
            {
                "Content": "現在還有人洗手台不是熱水嗎",
                "Vote": "→",
                "User": "james732",
                "Time": "01/17 19:22"
            },
            {
                "Content": "擬怎不尿在手上很溫暖又兼洗手嘻嘻",
                "Vote": "→",
                "User": "lewdster",
                "Time": "01/17 19:42"
            }
        ],
        "UpVote": 2,
        "DownVote": 2,
        "NoVote": 4,
        "Tag": "問卦"
    },
    {
        "Author": "gk1329",
        "Title": "未來世界買東西484不用錢",
        "Time": "2025-01-17T19:22:29",
        "Timestamp": 1737112949,
        "Responses": [
            {
                "Content": "手機0元，指定資費綁約n年啊",
                "Vote": "→",
                "User": "winglight",
                "Time": "01/17 19:28"
            },
            {
                "Content": "貸款一輩子",
                "Vote": "推",
                "User": "kanpfer",
                "Time": "01/17 19:29"
            },
            {
                "Content": "有種理論社會型態就是發固定點數給人民消費",
                "Vote": "→",
                "User": "heyd",
                "Time": "01/17 19:31"
            },
            {
                "Content": "上古時代也不用",
                "Vote": "→",
                "User": "pyrolith",
                "Time": "01/17 19:33"
            },
            {
                "Content": "steam 遊戲可以繼承 序號碼點一下 繼承人就繼承所有遊戲",
                "Vote": "→",
                "User": "mikiji",
                "Time": "01/17 19:42"
            },
            {
                "Content": "這是一個時代轉場的概念",
                "Vote": "→",
                "User": "mikiji",
                "Time": "01/17 19:56"
            },
            {
                "Content": "未來我猜手機會變成身份證 不用通信費 更有甚者 通信費會內化為人權之一 而沒有手機訊號者會成為法外份子",
                "Vote": "→",
                "User": "mikiji",
                "Time": "01/17 19:59"
            }
        ],
        "UpVote": 1,
        "DownVote": 0,
        "NoVote": 11,
        "Tag": "問卦"
    },
    {
        "Author": "TWipc",
        "Title": "認真文 大陸人覺得台灣很破怎麼辦",
        "Time": "2025-01-17T19:22:53",
        "Timestamp": 1737112973,
        "Responses": [
            {
                "Content": "中國人對台北評價就是三線城市跟廈 門差不多。",
                "Vote": "推",
                "User": "LoveMakeLove",
                "Time": "01/17 19:23"
            },
            {
                "Content": "對 超破 拜託不要來",
                "Vote": "→",
                "User": "cs09312",
                "Time": "01/17 19:23"
            },
            {
                "Content": "台灣交通安全",
                "Vote": "→",
                "User": "brother001",
                "Time": "01/17 19:23"
            },
            {
                "Content": "沒有自由的國家",
                "Vote": "→",
                "User": "opnash",
                "Time": "01/17 19:24"
            },
            {
                "Content": "說實話真的蠻破的",
                "Vote": "噓",
                "User": "derrick1220",
                "Time": "01/17 19:24"
            },
            {
                "Content": "上海有法租界，法國統治過的地方比日 本的漂亮不是正常嗎... 你那個新華路就是法租界啊",
                "Vote": "推",
                "User": "BRIANERIC2",
                "Time": "01/17 19:24"
            },
            {
                "Content": "破歸破 人民素質贏十條街 還是台灣舒服多",
                "Vote": "推",
                "User": "LBJ23K",
                "Time": "01/17 19:29"
            },
            {
                "Content": "實際走過確實文化氣息濃厚，但人民素質真",
                "Vote": "→",
                "User": "paufan",
                "Time": "01/17 19:29"
            },
            {
                "Content": "不要來最好。",
                "Vote": "→",
                "User": "kuangjc5566",
                "Time": "01/17 19:30"
            },
            {
                "Content": "用台灣比較落後的街道來比，怎麼不去比 先進的，笑死 要比就挑一樣的來比啊，會怕嗎",
                "Vote": "噓",
                "User": "showcoai",
                "Time": "01/17 19:31"
            },
            {
                "Content": "不然一堆往國外跑幹嘛",
                "Vote": "→",
                "User": "qaz12453",
                "Time": "01/17 19:32"
            },
            {
                "Content": "弄的越破他們說不定就不想要了",
                "Vote": "→",
                "User": "Hettt5655",
                "Time": "01/17 19:33"
            },
            {
                "Content": "國旅就那樣子沒法嘴",
                "Vote": "噓",
                "User": "ROTFL",
                "Time": "01/17 19:36"
            },
            {
                "Content": "台北市中山大安區很多街道都這樣阿 要拿夜市比吧，不過也是輸",
                "Vote": "→",
                "User": "a77774444",
                "Time": "01/17 19:36"
            },
            {
                "Content": "破敗的自由，乾淨的監獄",
                "Vote": "推",
                "User": "FakeBlack",
                "Time": "01/17 19:44"
            },
            {
                "Content": "問就是颱風 去年颱風過後 法租界梧桐也",
                "Vote": "→",
                "User": "dnawars",
                "Time": "01/17 19:48"
            },
            {
                "Content": "說實在的，比破，中國比台灣破，但 比先進的城市，中國一樣屌虐台灣， 所以才有北漂，x漂一詞",
                "Vote": "推",
                "User": "leohayashi1",
                "Time": "01/17 19:50"
            },
            {
                "Content": "只有憨鳥整天在意中國",
                "Vote": "噓",
                "User": "ohiu",
                "Time": "01/17 19:52"
            },
            {
                "Content": "他們可以去暖市啊，憨鳥都說超美",
                "Vote": "噓",
                "User": "bairn",
                "Time": "01/17 20:07"
            },
            {
                "Content": "傻鳥: 我不聽我不聽",
                "Vote": "→",
                "User": "bobju",
                "Time": "01/17 20:09"
            },
            {
                "Content": "who car",
                "Vote": "→",
                "User": "sustto",
                "Time": "01/17 20:25"
            },
            {
                "Content": "很破沒錯，千萬不要來台灣",
                "Vote": "推",
                "User": "tsujishiori",
                "Time": "01/17 20:47"
            },
            {
                "Content": "事實 辯駁沒意義 問題 講了二十幾年了 有沒有在改善？ 不過你挑圖 很偏頗 台灣可以找到一樣",
                "Vote": "推",
                "User": "judasprist",
                "Time": "01/17 20:47"
            },
            {
                "Content": "xfY4DaSfnDGlP",
                "Vote": "→",
                "User": "judasprist",
                "Time": "01/17 20:50"
            },
            {
                "Content": "拜託不要來",
                "Vote": "噓",
                "User": "lavena",
                "Time": "01/17 20:51"
            },
            {
                "Content": "「煙火氣」「人情味」一種懷舊氣氛",
                "Vote": "推",
                "User": "ling43235",
                "Time": "01/17 21:24"
            }
        ],
        "UpVote": 11,
        "DownVote": 6,
        "NoVote": 30,
        "Tag": "問卦"
    },
    {
        "Author": "zpeople0116",
        "Title": "我朋友對死刑邏輯很奇怪",
        "Time": "2025-01-17T19:23:26",
        "Timestamp": 1737113006,
        "Responses": [
            {
                "Content": "苗喬偉對吧",
                "Vote": "推",
                "User": "iamcnc",
                "Time": "01/17 19:28"
            },
            {
                "Content": "能教豬法律，這個厲害",
                "Vote": "→",
                "User": "whitenoise",
                "Time": "01/17 19:30"
            },
            {
                "Content": "你朋友是不是姓徐？名乃麟？輸不起？",
                "Vote": "→",
                "User": "sheep125",
                "Time": "01/17 19:33"
            },
            {
                "Content": "沒懶趴不要要求太多",
                "Vote": "推",
                "User": "bada",
                "Time": "01/17 20:06"
            }
        ],
        "UpVote": 3,
        "DownVote": 1,
        "NoVote": 4,
        "Tag": "問卦"
    },
    {
        "Author": "lovehandle",
        "Title": "日本人沒想像中有錢",
        "Time": "2025-01-17T19:23:50",
        "Timestamp": 1737113030,
        "Responses": [
            {
                "Content": "好了啦人家中位數就是比台灣高 連派遣也",
                "Vote": "→",
                "User": "fony1029",
                "Time": "01/17 19:26"
            },
            {
                "Content": "日本出國旅遊和留學比例超級低",
                "Vote": "推",
                "User": "gowang19",
                "Time": "01/17 19:26"
            },
            {
                "Content": "一堆月薪三萬的整天操人家的心",
                "Vote": "→",
                "User": "fony1029",
                "Time": "01/17 19:26"
            },
            {
                "Content": "日本政府負債10兆美元，這個國家快完了",
                "Vote": "推",
                "User": "jinx5566",
                "Time": "01/17 19:27"
            },
            {
                "Content": "祖國大日本帝國皇民，一級棒內",
                "Vote": "推",
                "User": "gameguy",
                "Time": "01/17 19:27"
            },
            {
                "Content": "台日薪資差不多啦 但台灣突飛猛進 日本不進反退",
                "Vote": "推",
                "User": "king123",
                "Time": "01/17 19:27"
            },
            {
                "Content": "只看到皇民整天吹然後賴在台灣不敢走",
                "Vote": "→",
                "User": "b9513227",
                "Time": "01/17 19:29"
            },
            {
                "Content": "日本的理髮師送貨員護士幼稚園老師",
                "Vote": "推",
                "User": "a49061854",
                "Time": "01/17 19:30"
            },
            {
                "Content": "日本人愛面子，不像台灣人整天跟政府哭",
                "Vote": "推",
                "User": "jacket664",
                "Time": "01/17 19:30"
            },
            {
                "Content": "之類的大部分都窮爆",
                "Vote": "→",
                "User": "a49061854",
                "Time": "01/17 19:30"
            },
            {
                "Content": "日本開個小餐館很賺錢",
                "Vote": "推",
                "User": "baobeising",
                "Time": "01/17 19:31"
            },
            {
                "Content": "日本藏富於民 跟中美反過來 你沒算 到財富前1/10000的那些財閥頭子",
                "Vote": "→",
                "User": "derrick1220",
                "Time": "01/17 19:31"
            },
            {
                "Content": "日本理髮師很窮嗎？歹丸的都月入十",
                "Vote": "→",
                "User": "ROTFL",
                "Time": "01/17 19:33"
            },
            {
                "Content": "人家買車這麼便宜",
                "Vote": "推",
                "User": "rex7125",
                "Time": "01/17 19:33"
            },
            {
                "Content": "你知道當台灣人已經不錯了吧",
                "Vote": "推",
                "User": "proprome",
                "Time": "01/17 19:36"
            },
            {
                "Content": "你知道照去年UBS資產金字塔來算 1億日幣 = 2000萬台幣也就大概6%嗎？ 以為日本沒錢，其實台灣也沒贏多少",
                "Vote": "推",
                "User": "RaiGend0519",
                "Time": "01/17 19:38"
            },
            {
                "Content": "中位數一定比私立科大餐飲系的高",
                "Vote": "→",
                "User": "b777787",
                "Time": "01/17 19:40"
            },
            {
                "Content": "兆八要有背景 正常都只有兆六",
                "Vote": "推",
                "User": "dufish81",
                "Time": "01/17 19:41"
            },
            {
                "Content": "真的假的，那我就是日本的4%來去當 日本人，我是不太信，前20%可能，前 發4%太扯了",
                "Vote": "推",
                "User": "leohayashi1",
                "Time": "01/17 19:43"
            },
            {
                "Content": "日本留學比例是少，但旅遊的話前10 年在美國到處可見日本人，現在真的 好少幾乎看不到，除了夏威夷",
                "Vote": "→",
                "User": "leohayashi1",
                "Time": "01/17 19:46"
            },
            {
                "Content": "去日本玩 導遊說日本市政府有錢人民沒",
                "Vote": "推",
                "User": "panda816",
                "Time": "01/17 19:46"
            },
            {
                "Content": "台灣已經屌打美國了 誰還管日本",
                "Vote": "推",
                "User": "a5110408123",
                "Time": "01/17 19:48"
            },
            {
                "Content": "日本在上個世紀經濟強盛時，大量投 資全世界優質資產，在海外累積的資 產高達8兆美元，每年收益高達4000 億美元。可不像台灣，稍微賺點錢就 幾百億、幾千億浪費掉。",
                "Vote": "推",
                "User": "splendidpoem",
                "Time": "01/17 19:52"
            },
            {
                "Content": "日本很想升息去槓桿啊 美國不給 日本只 能放著爛掉",
                "Vote": "→",
                "User": "FatFatQQ",
                "Time": "01/17 19:53"
            },
            {
                "Content": "笑死你看看街景，哪個像落後國家",
                "Vote": "推",
                "User": "STAEGG",
                "Time": "01/17 19:57"
            },
            {
                "Content": "日本買車要車位的 說便宜別笑死人了",
                "Vote": "推",
                "User": "lovecut",
                "Time": "01/17 19:58"
            },
            {
                "Content": "確實買什麼車位 台灣人都直接停路邊",
                "Vote": "噓",
                "User": "prince1226",
                "Time": "01/17 20:03"
            },
            {
                "Content": "真的啊外國要被尻很多稅",
                "Vote": "→",
                "User": "alex00089",
                "Time": "01/17 20:06"
            },
            {
                "Content": "台灣才是藏富於民，看詐騙案隨便都油水",
                "Vote": "推",
                "User": "EXZUSIC",
                "Time": "01/17 20:11"
            },
            {
                "Content": "每天的地鐵費用",
                "Vote": "推",
                "User": "u8702116",
                "Time": "01/17 20:14"
            },
            {
                "Content": "認真說 TMD鐵粉減少就是台灣越來越有錢",
                "Vote": "推",
                "User": "dinex",
                "Time": "01/17 20:19"
            },
            {
                "Content": "日本人主要是高就業率且薪水和社會 福利夠高，基本上靠薪水就能維持高 生活品質，不像華人韓國人有強烈延 遲享受和累積資產的想法",
                "Vote": "推",
                "User": "JackieShane",
                "Time": "01/17 20:24"
            },
            {
                "Content": "另外因為通縮和資產跌價太久了，沒 有累積資產的誘因，我日本朋友們大 多沒有在投資，再來因為遺產稅很高 所以也沒有代代累積繼承財產的誘因",
                "Vote": "→",
                "User": "JackieShane",
                "Time": "01/17 20:27"
            },
            {
                "Content": "總之在日本工作久了會發現那是一個 會消磨人努力動力的地方",
                "Vote": "→",
                "User": "JackieShane",
                "Time": "01/17 20:29"
            },
            {
                "Content": "但物價比台灣低啊",
                "Vote": "推",
                "User": "achun1212",
                "Time": "01/17 20:39"
            },
            {
                "Content": "看中位數就好了  台灣是日本的一半",
                "Vote": "推",
                "User": "Lowpapa",
                "Time": "01/17 20:46"
            },
            {
                "Content": "物價便宜是日幣狂貶 領當地薪也是吃不消",
                "Vote": "→",
                "User": "dinex",
                "Time": "01/17 20:54"
            },
            {
                "Content": "領當地薪花日幣 有什麼差 ==",
                "Vote": "→",
                "User": "Ashuya",
                "Time": "01/17 20:58"
            },
            {
                "Content": "中位數沒用，看房產增值幅度 老人手上好幾間，賣了1間吃很久",
                "Vote": "推",
                "User": "EXZUSIC",
                "Time": "01/17 21:17"
            },
            {
                "Content": "25萬税後剩20或19開頭，銀行業西裝還要 天天送洗，房租瓦斯水電又比台灣高很多 ，其實會過的比台灣刻苦的多得多",
                "Vote": "推",
                "User": "motorolaz",
                "Time": "01/17 21:55"
            },
            {
                "Content": "說物價低…沒感覺，回台灣後生活比在 日本省多了，不管外食或自己做",
                "Vote": "→",
                "User": "motorolaz",
                "Time": "01/17 21:57"
            },
            {
                "Content": "看房子幹嘛？你沒賣也是泡沫，要比還有 香港是台灣四倍",
                "Vote": "推",
                "User": "fony1029",
                "Time": "01/17 22:37"
            },
            {
                "Content": "薪水高，車價比台便宜一半，房價低 衣服包包都比台灣便宜 台灣才沒想像有錢吧?",
                "Vote": "推",
                "User": "akito117",
                "Time": "01/17 23:02"
            },
            {
                "Content": "我們有超貴房子破小國他們有啥呢",
                "Vote": "推",
                "User": "h034826567",
                "Time": "01/18 08:45"
            },
            {
                "Content": "台日家戶可支配所得快打平了，日本也是",
                "Vote": "推",
                "User": "qaz630210",
                "Time": "01/19 16:03"
            }
        ],
        "UpVote": 30,
        "DownVote": 1,
        "NoVote": 47,
        "Tag": "問卦"
    },
    {
        "Author": "cattielin",
        "Title": "沒法治規定要政府幹嘛？廢死",
        "Time": "2025-01-17T19:24:03",
        "Timestamp": 1737113043,
        "Responses": [
            {
                "Content": "你知道歐美有多少先進人權國家廢死嗎",
                "Vote": "→",
                "User": "james732",
                "Time": "01/17 19:24"
            },
            {
                "Content": "你有遵守交通規則嗎",
                "Vote": "→",
                "User": "pyrolith",
                "Time": "01/17 19:27"
            }
        ],
        "UpVote": 0,
        "DownVote": 0,
        "NoVote": 2,
        "Tag": "問卦"
    },
    {
        "Author": "shelovesme",
        "Title": "奶水被斷了怎麼辦？",
        "Time": "2025-01-17T19:25:42",
        "Timestamp": 1737113142,
        "Responses": [
            {
                "Content": "該自己吃固態食物ㄌ",
                "Vote": "推",
                "User": "heyd",
                "Time": "01/17 19:27"
            },
            {
                "Content": "去找正常工作或外送",
                "Vote": "→",
                "User": "LoveMakeLove",
                "Time": "01/17 19:28"
            },
            {
                "Content": "生命會自己找到出路",
                "Vote": "推",
                "User": "yc410",
                "Time": "01/17 19:30"
            }
        ],
        "UpVote": 3,
        "DownVote": 1,
        "NoVote": 3,
        "Tag": "問卦"
    },
    {
        "Author": "skn60694",
        "Title": "有人畢業後才發現被班上腐女嗑CP嗎?",
        "Time": "2025-01-17T19:26:16",
        "Timestamp": 1737113176,
        "Responses": [
            {
                "Content": "發現被班上甲甲意淫過",
                "Vote": "→",
                "User": "s999132",
                "Time": "01/17 19:45"
            },
            {
                "Content": "呃呃 怎麼即視感這麼重",
                "Vote": "推",
                "User": "a34567",
                "Time": "01/17 19:49"
            },
            {
                "Content": "現在小女生嗑CP的很多，像我高一的 女兒也愛嗑，但不會嗑同年齢的男CP ，因為她覺得同年齡的男生都太傻B.",
                "Vote": "推",
                "User": "paul0407",
                "Time": "01/17 19:59"
            }
        ],
        "UpVote": 2,
        "DownVote": 1,
        "NoVote": 5,
        "Tag": "問卦"
    },
    {
        "Author": "dean1990",
        "Title": "必勝客，達美樂，都幾？",
        "Time": "2025-01-17T19:26:26",
        "Timestamp": 1737113186,
        "Responses": [
            {
                "Content": "講了半天你買筆管麵 洗勒靠",
                "Vote": "→",
                "User": "cs09312",
                "Time": "01/17 19:27"
            },
            {
                "Content": "我家巷口小店 大披薩210料比必勝客多",
                "Vote": "→",
                "User": "a27588679",
                "Time": "01/17 19:28"
            },
            {
                "Content": "SUBWAY",
                "Vote": "噓",
                "User": "linceass",
                "Time": "01/17 19:28"
            },
            {
                "Content": "點二個大披薩還送二杯中飲",
                "Vote": "→",
                "User": "a27588679",
                "Time": "01/17 19:28"
            },
            {
                "Content": "有火山的是哪一家，一直看到廣告",
                "Vote": "→",
                "User": "yzelly",
                "Time": "01/17 19:29"
            },
            {
                "Content": "扁她阿 吃啥筆管麵",
                "Vote": "→",
                "User": "yulis",
                "Time": "01/17 19:35"
            },
            {
                "Content": "這兩家我選達美樂",
                "Vote": "推",
                "User": "bye2007",
                "Time": "01/17 19:39"
            },
            {
                "Content": "8825252VS3939889",
                "Vote": "推",
                "User": "kyosukeakiba",
                "Time": "01/17 19:39"
            },
            {
                "Content": "為了健康 都不吃 嘻嘻",
                "Vote": "→",
                "User": "buslover",
                "Time": "01/17 19:40"
            },
            {
                "Content": "拿坡里，但以前必勝客很好吃",
                "Vote": "推",
                "User": "willia5566",
                "Time": "01/17 19:42"
            },
            {
                "Content": "拿坡里>必勝客>>>>>>達美樂 狗逼達美樂賣騙人折價券 我一輩子黑",
                "Vote": "推",
                "User": "Hsu1025",
                "Time": "01/17 19:45"
            },
            {
                "Content": "必勝客太油了",
                "Vote": "→",
                "User": "lavender225",
                "Time": "01/17 19:46"
            },
            {
                "Content": "芝心很好ㄘ餒",
                "Vote": "推",
                "User": "AHHHHH",
                "Time": "01/17 19:57"
            },
            {
                "Content": "最難吃的就好市多 幹",
                "Vote": "推",
                "User": "ahw12000",
                "Time": "01/17 20:16"
            }
        ],
        "UpVote": 9,
        "DownVote": 1,
        "NoVote": 11,
        "Tag": "問卦"
    },
    {
        "Author": "a2251325",
        "Title": "不敢講廢死是因為怕清割嗎",
        "Time": "2025-01-17T19:27:46",
        "Timestamp": 1737113266,
        "Responses": [
            {
                "Content": "所以到底是哥還是嫂？",
                "Vote": "推",
                "User": "sheep125",
                "Time": "01/17 19:32"
            }
        ],
        "UpVote": 1,
        "DownVote": 0,
        "NoVote": 1,
        "Tag": "問卦"
    }
]