[
    {
        "Author": "copybrown",
        "Title": "假摔的技巧",
        "Time": "2024-12-19T08:52:56",
        "Timestamp": 1734569576,
        "Responses": [
            {
                "Content": "先叫旁邊不能錄影",
                "Vote": "推",
                "User": "EfiwymsiAros",
                "Time": "12/19 08:53"
            },
            {
                "Content": "可以去狗熊學院學習",
                "Vote": "→",
                "User": "gn134679",
                "Time": "12/19 08:54"
            },
            {
                "Content": "內馬爾 應該是經典吧",
                "Vote": "→",
                "User": "max95624",
                "Time": "12/19 08:54"
            },
            {
                "Content": "自備香蕉皮",
                "Vote": "→",
                "User": "jma306",
                "Time": "12/19 08:54"
            },
            {
                "Content": "要熟悉牛頓第三運動定律",
                "Vote": "→",
                "User": "vowpool",
                "Time": "12/19 08:55"
            },
            {
                "Content": "問問董至成？",
                "Vote": "→",
                "User": "kevinlie",
                "Time": "12/19 08:55"
            },
            {
                "Content": "旁邊青鳥豬隊友不夠力",
                "Vote": "→",
                "User": "abbjesper",
                "Time": "12/19 08:55"
            },
            {
                "Content": "昨天那隻鳥好糗 笑死",
                "Vote": "推",
                "User": "ZXCVBNM9999",
                "Time": "12/19 09:10"
            },
            {
                "Content": "大師兄嬌喘一聲倒在何金銀懷裡",
                "Vote": "推",
                "User": "DogBe106",
                "Time": "12/19 09:29"
            },
            {
                "Content": "隊友要技巧性遮住敵方攝像機",
                "Vote": "→",
                "User": "Yahweh",
                "Time": "12/19 09:51"
            }
        ],
        "UpVote": 7,
        "DownVote": 0,
        "NoVote": 9,
        "Tag": "問卦"
    },
    {
        "Author": "leo921080931",
        "Title": "突然發現自己看了50幾話bl漫畫怎麼辦",
        "Time": "2024-12-19T08:55:00",
        "Timestamp": 1734569700,
        "Responses": [
            {
                "Content": "去甲板啊 還問",
                "Vote": "→",
                "User": "elec1141",
                "Time": "12/19 08:55"
            },
            {
                "Content": "就承認自己是彎的很難嗎",
                "Vote": "→",
                "User": "binco",
                "Time": "12/19 08:55"
            },
            {
                "Content": "你看之前沒有先了解這部是BL嗎？",
                "Vote": "推",
                "User": "angelology",
                "Time": "12/19 08:57"
            },
            {
                "Content": "我直接棄坑  一開始看的某個漫畫也是沒 有標BL的標籤 去找才發現",
                "Vote": "→",
                "User": "qaz223gy",
                "Time": "12/19 09:06"
            },
            {
                "Content": "出去右轉甲版 你要的答案都在那",
                "Vote": "推",
                "User": "pirtheda",
                "Time": "12/19 09:15"
            },
            {
                "Content": "第一季R15、第二季R18會開車欸，去看 真正的少年漫和你喜歡的百合吧",
                "Vote": "→",
                "User": "angelology",
                "Time": "12/19 09:20"
            }
        ],
        "UpVote": 4,
        "DownVote": 0,
        "NoVote": 9,
        "Tag": "問卦"
    },
    {
        "Author": "zxc0312",
        "Title": "澤倫斯基接下來要怎麼談判才能贏？",
        "Time": "2024-12-19T08:58:47",
        "Timestamp": 1734569927,
        "Responses": [
            {
                "Content": "再用滑板車炸彈炸幾個將領",
                "Vote": "→",
                "User": "fantasyth",
                "Time": "12/19 08:59"
            },
            {
                "Content": "三上優雅",
                "Vote": "→",
                "User": "jma306",
                "Time": "12/19 08:59"
            },
            {
                "Content": "學蔣介石擺爛放在那邊給後人處理",
                "Vote": "推",
                "User": "LoveMakeLove",
                "Time": "12/19 09:00"
            },
            {
                "Content": "然後邀西方為主的聯合國維和部隊入駐 最近剛炸了一個二星上將，多炸幾個 鵝國高官就會怕了",
                "Vote": "→",
                "User": "fantasyth",
                "Time": "12/19 09:00"
            },
            {
                "Content": "(學蔣介石擺爛) 老蔣時代幫清朝擦屁股還錢 還有一堆的租借也無法取消。  是二戰勝利 才順勢取消掉很多賠款條約+租界歸還 後來毛匪韓戰打得不錯 俄國才歸還旅順和鐵",
                "Vote": "→",
                "User": "jma306",
                "Time": "12/19 09:03"
            },
            {
                "Content": "蔣毛要處理中國的問題  很不容易的",
                "Vote": "→",
                "User": "jma306",
                "Time": "12/19 09:05"
            },
            {
                "Content": "找軍武板板眾 一人一口嘴砲 砲死普丁啊",
                "Vote": "推",
                "User": "whizz",
                "Time": "12/19 09:06"
            },
            {
                "Content": "至於丟掉大陸是因為戰後經濟政策失敗  經 濟崩掉。  敘利亞阿薩德政府長期被制裁 經濟也是很慘  是倒臺的重要原因之一",
                "Vote": "→",
                "User": "jma306",
                "Time": "12/19 09:07"
            },
            {
                "Content": "當布丁司機",
                "Vote": "推",
                "User": "angelo98",
                "Time": "12/19 09:15"
            },
            {
                "Content": "花錢找猶太團體幫忙遊說如何像以色列",
                "Vote": "→",
                "User": "driver0811",
                "Time": "12/19 09:22"
            },
            {
                "Content": "當然歹拖繼續打，不然就要被清算了",
                "Vote": "推",
                "User": "krosiswang01",
                "Time": "12/19 09:25"
            }
        ],
        "UpVote": 5,
        "DownVote": 0,
        "NoVote": 15,
        "Tag": "問卦"
    },
    {
        "Author": "MeeToo",
        "Title": "火鍋店大夜班45k還會缺人嗎",
        "Time": "2024-12-19T08:59:12",
        "Timestamp": 1734569952,
        "Responses": [
            {
                "Content": "那就降價去找外勞，台勞不敢找外勞幹",
                "Vote": "推",
                "User": "boy1031",
                "Time": "12/19 09:01"
            },
            {
                "Content": "錢都對不對",
                "Vote": "噓",
                "User": "k385476916",
                "Time": "12/19 09:06"
            },
            {
                "Content": "党：即將有一批印度移工很便宜呢",
                "Vote": "→",
                "User": "ethanwu0414",
                "Time": "12/19 09:10"
            },
            {
                "Content": "凸( ﾟдﾟ)凸海報在哪啦贛",
                "Vote": "→",
                "User": "meta41110",
                "Time": "12/19 09:22"
            },
            {
                "Content": "2F跟蹤我？",
                "Vote": "→",
                "User": "MeeToo",
                "Time": "12/19 09:25"
            }
        ],
        "UpVote": 1,
        "DownVote": 1,
        "NoVote": 3,
        "Tag": "問卦"
    },
    {
        "Author": "youdontsay",
        "Title": "為何納粹要派黨衛軍出征在野黨？",
        "Time": "2024-12-19T08:59:44",
        "Timestamp": 1734569984,
        "Responses": [
            {
                "Content": "閩南雅利安人",
                "Vote": "推",
                "User": "bicedb",
                "Time": "12/19 09:01"
            },
            {
                "Content": "為了抵抗蘇聯共產黨的滲透亂政阿",
                "Vote": "推",
                "User": "max60209",
                "Time": "12/19 09:01"
            },
            {
                "Content": "無恥那需要理由,對他們來說是生活",
                "Vote": "推",
                "User": "konanno1",
                "Time": "12/19 09:03"
            },
            {
                "Content": "在台灣上演中",
                "Vote": "推",
                "User": "s9056017",
                "Time": "12/19 09:03"
            },
            {
                "Content": "沒有 都是善意cc 大概這樣",
                "Vote": "→",
                "User": "ctx1000",
                "Time": "12/19 09:08"
            },
            {
                "Content": "歷史都會不停的重複",
                "Vote": "→",
                "User": "liquidgroove",
                "Time": "12/19 09:10"
            },
            {
                "Content": "這段歷史會建議多去了解美國尤其猶太人 介入的程式(雖然幾年後猶太人被整肅，其",
                "Vote": "推",
                "User": "peterwu4",
                "Time": "12/19 10:21"
            },
            {
                "Content": "實也有關 ^度 像賓拉登當初是不是在蘇聯入侵阿富汗時 和美國併肩一起作戰十年，十年啊孩子，",
                "Vote": "→",
                "User": "peterwu4",
                "Time": "12/19 10:23"
            }
        ],
        "UpVote": 5,
        "DownVote": 0,
        "NoVote": 8,
        "Tag": "問卦"
    },
    {
        "Author": "a22028504",
        "Title": "吃太鹹隔天必水腫？",
        "Time": "2024-12-19T09:00:07",
        "Timestamp": 1734570007,
        "Responses": [
            {
                "Content": "沒吃鹽也是腫的",
                "Vote": "→",
                "User": "bill403777",
                "Time": "12/19 09:02"
            },
            {
                "Content": "鈉含量高的食物都會",
                "Vote": "→",
                "User": "kongtson",
                "Time": "12/19 09:12"
            },
            {
                "Content": "驗一下腎指數？",
                "Vote": "推",
                "User": "TienWo",
                "Time": "12/19 10:28"
            }
        ],
        "UpVote": 1,
        "DownVote": 0,
        "NoVote": 4,
        "Tag": "問卦"
    },
    {
        "Author": "iPhoneX3",
        "Title": "下午5點後的工地保全太涼了？",
        "Time": "2024-12-19T09:00:43",
        "Timestamp": 1734570043,
        "Responses": [
            {
                "Content": "有人做就不錯了",
                "Vote": "推",
                "User": "gn134679",
                "Time": "12/19 09:01"
            },
            {
                "Content": "你沒有裝備進工地很危險也有工安疑",
                "Vote": "推",
                "User": "albertfeng",
                "Time": "12/19 09:03"
            },
            {
                "Content": "你是因為被保全兇才酸言酸語 心胸狹窄",
                "Vote": "推",
                "User": "jerrys0580",
                "Time": "12/19 09:03"
            },
            {
                "Content": "工地就一個小亭子有啥好爽的 有的連亭子都沒有 晚上還要提防小偷 去偷工具鋼筋 我朋友在台南豪宅當保全 有冷氣冰箱",
                "Vote": "→",
                "User": "luciffar",
                "Time": "12/19 09:04"
            },
            {
                "Content": "下班還可以上樓幹80歲老貴婦 超暖超緊^^",
                "Vote": "→",
                "User": "luciffar",
                "Time": "12/19 09:06"
            },
            {
                "Content": "你一個路人他可以不屌你 有理你就不錯了",
                "Vote": "推",
                "User": "RLAPH",
                "Time": "12/19 09:06"
            },
            {
                "Content": "我有總幹事證照 也當過酒廠保全 真的這",
                "Vote": "→",
                "User": "iPhoneX3",
                "Time": "12/19 09:08"
            },
            {
                "Content": "怕有人進去偷東西 想不開～ 影響進度",
                "Vote": "推",
                "User": "anyu0805",
                "Time": "12/19 09:21"
            },
            {
                "Content": "晚上很危險，一覺醒來，工地被搬空 或是太冷，一覺醒來，已經在黃泉路",
                "Vote": "推",
                "User": "WestRiver0tp",
                "Time": "12/19 09:38"
            },
            {
                "Content": "那種沒人的荒涼工地很可怕吧？如果有小偷要 阻止搞不好會有生命危險",
                "Vote": "→",
                "User": "lst77",
                "Time": "12/19 09:43"
            },
            {
                "Content": "很難熬很折磨啊",
                "Vote": "推",
                "User": "garybawbaw",
                "Time": "12/19 09:53"
            }
        ],
        "UpVote": 9,
        "DownVote": 0,
        "NoVote": 15,
        "Tag": "問卦"
    },
    {
        "Author": "Recoverism",
        "Title": "中國有被台灣收買的藝人或網紅嗎？",
        "Time": "2024-12-19T09:02:06",
        "Timestamp": 1734570126,
        "Responses": [
            {
                "Content": "應該沒有 因為這樣對方回去會被關",
                "Vote": "推",
                "User": "nk",
                "Time": "12/19 09:03"
            },
            {
                "Content": "家人也會受到波及吧",
                "Vote": "推",
                "User": "jamison33",
                "Time": "12/19 09:19"
            },
            {
                "Content": "可以去B站發個視頻呀,只要用詞有問題,封",
                "Vote": "推",
                "User": "castille",
                "Time": "12/19 09:33"
            },
            {
                "Content": "台灣又沒有要併吞中國，沒必要",
                "Vote": "→",
                "User": "krousxchen",
                "Time": "12/19 09:37"
            },
            {
                "Content": "馬上會被共匪消滅",
                "Vote": "推",
                "User": "deadogy",
                "Time": "12/19 21:50"
            }
        ],
        "UpVote": 5,
        "DownVote": 0,
        "NoVote": 2,
        "Tag": "問卦"
    },
    {
        "Author": "frzqp3814396",
        "Title": "傻鳥們是不是真的過很爽",
        "Time": "2024-12-19T09:04:56",
        "Timestamp": 1734570296,
        "Responses": [
            {
                "Content": "活在自己的世界。",
                "Vote": "推",
                "User": "LoveMakeLove",
                "Time": "12/19 09:05"
            },
            {
                "Content": "黨會五鬼搬運養啊！個個吃香喝辣的",
                "Vote": "→",
                "User": "edgeking",
                "Time": "12/19 09:06"
            },
            {
                "Content": "有領錢辦事就算了，沒有那真的要去",
                "Vote": "→",
                "User": "LoveMakeLove",
                "Time": "12/19 09:06"
            },
            {
                "Content": "掙錢嘛 生意 不寒摻",
                "Vote": "推",
                "User": "ieyfung",
                "Time": "12/19 09:07"
            },
            {
                "Content": "用外部爭端轉移內在爭端啊",
                "Vote": "推",
                "User": "EfiwymsiAros",
                "Time": "12/19 09:09"
            },
            {
                "Content": "他們真的要確定柯文哲有罪就可以安心了 就算內政炸裂：終於教訓了柯文哲",
                "Vote": "推",
                "User": "fony1029",
                "Time": "12/19 09:10"
            },
            {
                "Content": "我問你 要給你多少錢 你才願意躺在地上說 像條狗一樣誣賴別人？ 如果那個躺在地上耍賴的青鳥 其實沒有比我們笨的話 細思極恐 要給多少利益 才能讓一個正常人願意這樣毒害台灣？ 誰給的出這麼多利益 讓人趴在地上變成狗？",
                "Vote": "推",
                "User": "eyesg",
                "Time": "12/19 09:11"
            },
            {
                "Content": "電商折扣碼賣出一筆能抽成比較爽吧？",
                "Vote": "噓",
                "User": "x941u4vu86",
                "Time": "12/19 09:22"
            },
            {
                "Content": "某些打手就党給的錢夠多吧",
                "Vote": "推",
                "User": "dbjdx",
                "Time": "12/19 09:25"
            },
            {
                "Content": "通膨什麼的是父母要面對的 自己負責 拿錢來爽就好",
                "Vote": "→",
                "User": "ashjkn5586",
                "Time": "12/19 09:35"
            },
            {
                "Content": "啥鳥們很咨足",
                "Vote": "→",
                "User": "newqazwsx",
                "Time": "12/19 09:38"
            },
            {
                "Content": "詐騙爛成這樣",
                "Vote": "推",
                "User": "funmilk",
                "Time": "12/19 09:56"
            },
            {
                "Content": "你怎麼不說藍白怎麼不好好立這些法？",
                "Vote": "→",
                "User": "imhideji",
                "Time": "12/19 10:31"
            }
        ],
        "UpVote": 8,
        "DownVote": 1,
        "NoVote": 18,
        "Tag": "問卦"
    },
    {
        "Author": "anonymitet",
        "Title": "這家咖啡廳 賣的咖啡好像會醒腦☺",
        "Time": "2024-12-19T09:05:02",
        "Timestamp": 1734570302,
        "Responses": [
            {
                "Content": "我好興奮啊.jpg",
                "Vote": "推",
                "User": "rsom",
                "Time": "12/19 09:08"
            },
            {
                "Content": "這腿用起來會啪啪響 奶不小又白 還漂亮",
                "Vote": "推",
                "User": "Dinenger",
                "Time": "12/19 09:11"
            },
            {
                "Content": "凸( ﾟдﾟ)凸番號",
                "Vote": "→",
                "User": "meta41110",
                "Time": "12/19 09:21"
            },
            {
                "Content": "馬的 哪一家",
                "Vote": "→",
                "User": "nvlsvee",
                "Time": "12/19 09:27"
            },
            {
                "Content": "這是女優嗎？",
                "Vote": "推",
                "User": "system303179",
                "Time": "12/20 09:59"
            }
        ],
        "UpVote": 4,
        "DownVote": 0,
        "NoVote": 2,
        "Tag": "問卦"
    },
    {
        "Author": "Kimmy",
        "Title": "折折買幾億的美債還好嗎？?",
        "Time": "2024-12-19T09:05:11",
        "Timestamp": 1734570311,
        "Responses": [
            {
                "Content": "現在跌爛還不趕快買？",
                "Vote": "推",
                "User": "thegreatlcx",
                "Time": "12/19 09:06"
            }
        ],
        "UpVote": 1,
        "DownVote": 0,
        "NoVote": 0,
        "Tag": "問卦"
    },
    {
        "Author": "joveryant",
        "Title": "請問小粉紅來破壞台灣的民主 開心嗎?",
        "Time": "2024-12-19T09:05:44",
        "Timestamp": 1734570344,
        "Responses": [
            {
                "Content": "好了啦 台灣60%都是小粉紅對吧",
                "Vote": "噓",
                "User": "ZXCVBNM9999",
                "Time": "12/19 09:06"
            },
            {
                "Content": "飼料費被凍結 出來汪幾聲錯了嗎?",
                "Vote": "→",
                "User": "sunluna",
                "Time": "12/19 09:07"
            },
            {
                "Content": "中國人經過 寸草不生",
                "Vote": "→",
                "User": "Barbarian123",
                "Time": "12/19 09:08"
            },
            {
                "Content": "翻譯：不挺民進黨的都是中國人",
                "Vote": "噓",
                "User": "garyasdf",
                "Time": "12/19 09:10"
            },
            {
                "Content": "我只要註冊需要手機的我都不敢註冊 綠共的 網站我也漸漸變成這樣了",
                "Vote": "→",
                "User": "EXIONG",
                "Time": "12/19 09:15"
            },
            {
                "Content": "我覺得綠色漸漸變成紅共 也沒差 頂多不註 冊需要手機的網站",
                "Vote": "→",
                "User": "EXIONG",
                "Time": "12/19 09:17"
            },
            {
                "Content": "統戰經費多 拿錢辦事，天經地義",
                "Vote": "→",
                "User": "pengdio",
                "Time": "12/19 09:20"
            },
            {
                "Content": "人民會怎樣  青鳥會飛出來",
                "Vote": "→",
                "User": "jma306",
                "Time": "12/19 09:21"
            },
            {
                "Content": "民進黨就是該死",
                "Vote": "噓",
                "User": "haroldliu",
                "Time": "12/19 09:26"
            },
            {
                "Content": "爛不能罵哦",
                "Vote": "推",
                "User": "regzheng325",
                "Time": "12/19 09:37"
            },
            {
                "Content": "對自己國內的執政黨腐爛視而不見，只在 怪在野不支持綠蟾蜍？！？不知道已經被 國際認證支持戒嚴嗎？，抹紅別人是小粉 紅？？？現在台灣正在發生文革，沒看見",
                "Vote": "→",
                "User": "measure22",
                "Time": "12/19 10:00"
            },
            {
                "Content": "破防囉憨鳥",
                "Vote": "→",
                "User": "idxxxx",
                "Time": "12/19 10:08"
            }
        ],
        "UpVote": 1,
        "DownVote": 4,
        "NoVote": 17,
        "Tag": "問卦"
    }
]